sanex/__init__.py
sanex/cleaner.py
sanex/functions/__init__.py
sanex/functions/_clean_column_names.py
sanex/functions/_drop_single_value_columns.py
sanex/functions/_enforce_data_types.py
sanex/functions/_extract_and_clean_numeric.py
sanex/functions/_extract_currency.py
sanex/functions/_extract_email.py
sanex/functions/_extract_phone_numbers.py
sanex/functions/_extract_urls.py
sanex/functions/_extract_with_regex.py
sanex/functions/_flag_for_review.py
sanex/functions/_format_for_display.py
sanex/functions/_generate_synthetic.py
sanex/functions/_handle_outliers.py
sanex/functions/_impute_values.py
sanex/functions/_infer_gender.py
sanex/functions/_infer_types.py
sanex/functions/_missing_data.py
sanex/functions/_remove_duplicates.py
sanex/functions/_remove_html.py
sanex/functions/_remove_pii.py
sanex/functions/_remove_punctuation.py
sanex/functions/_remove_special_characters.py
sanex/functions/_remove_stopwords.py
sanex/functions/_remove_unwanted_rows_and_cols.py
sanex/functions/_replace_text.py
sanex/functions/_standardize_booleans.py
sanex/functions/_standardize_categorical_values.py
sanex/functions/_standardize_units.py
sanex/functions/_summarize_missing_data.py
sanex/functions/_whitespace.py
sanex-0.3.0.dist-info/licenses/LICENSE
sanex-0.3.0.dist-info/METADATA
sanex-0.3.0.dist-info/WHEEL
sanex-0.3.0.dist-info/top_level.txt
sanex-0.3.0.dist-info/RECORD
